httpcode/__init__.py
httpcode-0.6.dist-info/DESCRIPTION.rst
httpcode-0.6.dist-info/METADATA
httpcode-0.6.dist-info/RECORD
httpcode-0.6.dist-info/WHEEL
httpcode-0.6.dist-info/entry_points.txt
httpcode-0.6.dist-info/metadata.json
httpcode-0.6.dist-info/top_level.txt
