Metadata-Version: 2.0
Name: httpcode
Version: 0.6
Summary: httpcode - explain HTTP status code
Home-page: http://github.com/rspivak/httpcode
Author: Ruslan Spivak
Author-email: ruslan.spivak@gmail.com
License: MIT
Platform: UNKNOWN
Classifier: Intended Audience :: Developers
Classifier: License :: OSI Approved :: MIT License
Classifier: Programming Language :: Python
Classifier: Programming Language :: Python :: 2.7
Classifier: Programming Language :: Python :: 3
Classifier: Topic :: Internet :: WWW/HTTP
Classifier: Operating System :: Unix
Requires-Dist: colorama
Provides-Extra: test
